programs/alpha_beta.py
programs/alphabeta.py
programs/ann_backward.py
programs/ann_prgm.py
programs/ann_xor.py
programs/astar.py
programs/bfs.py
programs/cnn.py
programs/csp.py
programs/dfs.py
programs/ffnn.py
programs/genetic_algorithm.py
programs/hill_climbing.py
programs/maze_rl.py
programs/minimax.py
programs/q_learning.py
programs/rnn.py
programs/simulated_annealing.py
programs/tsp_bruteforce.py
programs/water_jug.py
programs/wumpus_world.py
labcli_s44044-0.1.1.dist-info/METADATA
labcli_s44044-0.1.1.dist-info/WHEEL
labcli_s44044-0.1.1.dist-info/entry_points.txt
labcli_s44044-0.1.1.dist-info/top_level.txt
labcli_s44044-0.1.1.dist-info/RECORD
