Metadata-Version: 2.4
Name: labcli-s44044
Version: 0.1.1
Summary: A simple CLI to list and run lab programs
Author-email: Shakthivel C <shakthic007@gmail.com>
License-Expression: MIT
Requires-Python: >=3.8
